dungngo_upsonic-0.60.1.dist-info/licenses/LICENCE
upsonic/__init__.py
upsonic/py.typed
upsonic/tools.py
upsonic/agent/__init__.py
upsonic/agent/agent.py
upsonic/agent/base.py
upsonic/agent/context_managers/__init__.py
upsonic/agent/context_managers/call_manager.py
upsonic/agent/context_managers/context_manager.py
upsonic/agent/context_managers/llm_manager.py
upsonic/agent/context_managers/memory_manager.py
upsonic/agent/context_managers/reliability_manager.py
upsonic/agent/context_managers/storage_manager.py
upsonic/agent/context_managers/system_prompt_manager.py
upsonic/agent/context_managers/task_manager.py
upsonic/canvas/__init__.py
upsonic/canvas/canvas.py
upsonic/context/__init__.py
upsonic/context/agent.py
upsonic/context/default_prompt.py
upsonic/context/sources.py
upsonic/context/task.py
upsonic/eval/__init__.py
upsonic/eval/accuracy.py
upsonic/eval/models.py
upsonic/eval/performance.py
upsonic/eval/reliability.py
upsonic/graph/__init__.py
upsonic/graph/graph.py
upsonic/knowledge_base/__init__.py
upsonic/knowledge_base/knowledge_base.py
upsonic/memory/__init__.py
upsonic/memory/memory.py
upsonic/models/__init__.py
upsonic/models/base.py
upsonic/models/providers.py
upsonic/models/utils.py
upsonic/reliability_layer/reliability_layer.py
upsonic/schemas/__init__.py
upsonic/schemas/user.py
upsonic/storage/__init__.py
upsonic/storage/base.py
upsonic/storage/types.py
upsonic/storage/memory/__init__.py
upsonic/storage/memory/memory.py
upsonic/storage/providers/__init__.py
upsonic/storage/providers/in_memory.py
upsonic/storage/providers/json.py
upsonic/storage/providers/mongo.py
upsonic/storage/providers/postgres.py
upsonic/storage/providers/redis.py
upsonic/storage/providers/sqlite.py
upsonic/storage/session/__init__.py
upsonic/storage/session/sessions.py
upsonic/tasks/tasks.py
upsonic/team/__init__.py
upsonic/team/context_sharing.py
upsonic/team/coordinator_setup.py
upsonic/team/delegation_manager.py
upsonic/team/result_combiner.py
upsonic/team/task_assignment.py
upsonic/team/team.py
upsonic/tools/__init__.py
dungngo_upsonic-0.60.1.dist-info/METADATA
dungngo_upsonic-0.60.1.dist-info/WHEEL
dungngo_upsonic-0.60.1.dist-info/top_level.txt
dungngo_upsonic-0.60.1.dist-info/RECORD
