Metadata-Version: 2.4
Name: dungngo-upsonic
Version: 0.60.1
Summary: Task oriented AI agent framework for digital workers and vertical AI agents (republished for testing)
Author-email: dungngo <test@dungngo.dev>
Requires-Python: >=3.10
License-File: LICENCE
Requires-Dist: psutil==6.1.1
Requires-Dist: rich>=13.9.4
Requires-Dist: sentry-sdk[opentelemetry]>=2.19.2
Requires-Dist: toml>=0.10.2
Requires-Dist: uv>=0.5.20
Requires-Dist: mcp[cli]==1.9.4
Requires-Dist: pydantic-ai==0.3.2
Requires-Dist: python-dotenv>=1.0.1
Requires-Dist: uvicorn>=0.34.0
Requires-Dist: beautifulsoup4>=4.12.3
Requires-Dist: boto3>=1.35.99
Requires-Dist: botocore>=1.35.99
Requires-Dist: google>=3.0.0
Requires-Dist: markitdown[all]==0.0.1
Requires-Dist: python-multipart>=0.0.20
Requires-Dist: requests>=2.32.3
Requires-Dist: duckduckgo-search>=7.3.1
Requires-Dist: nest-asyncio>=1.6.0
Requires-Dist: pydantic-ai-slim[anthropic,bedrock,mcp,openai]>=0.3.2
Requires-Dist: pydantic==2.10.5
Requires-Dist: celery[redis]>=5.5.3
Provides-Extra: rag
Requires-Dist: future>=1.0.0; extra == "rag"
Requires-Dist: graspologic>=3.4.1; extra == "rag"
Requires-Dist: lightrag-hku==1.2.6; extra == "rag"
Requires-Dist: pipmaster>=0.5.1; extra == "rag"
Requires-Dist: tenacity>=9.0.0; extra == "rag"
Requires-Dist: tiktoken>=0.9.0; extra == "rag"
Provides-Extra: storage
Requires-Dist: aiosqlite>=0.21.0; extra == "storage"
Requires-Dist: asyncpg>=0.30.0; extra == "storage"
Requires-Dist: greenlet>=3.2.3; extra == "storage"
Requires-Dist: motor>=3.7.1; extra == "storage"
Requires-Dist: psycopg2-binary>=2.9.10; extra == "storage"
Requires-Dist: psycopg[binary]>=3.2.9; extra == "storage"
Requires-Dist: redis>=5.2.1; extra == "storage"
Requires-Dist: sqlalchemy>=2.0.42; extra == "storage"
Dynamic: license-file
